<?xml version="1.0" encoding="utf-8" ?>
<Settings>
    <Setting Key="ima9ines.Nop.BaoKim.PluginSeName">
        <Value>bao-kim-plugin/</Value>
    </Setting>
    <Setting Key="ima9ines.Nop.BaoKim.RateUri">
        <Value>http://www.nopcommerce.com/p/1744/bao-kim-embed-code-button-free-ima9inescom.aspx</Value>
    </Setting>
    <Setting Key="ima9ines.Nop.BaoKim.SuggestFeaturesUri">
        <Value>https://github.com/ima9ines/nopCommerce/issues</Value>
    </Setting>
    <Setting Key="ima9ines.Nop.BaoKim.HelpUri">
        <Value>https://github.com/ima9ines/nopCommerce/wiki/bao-kim-plugin</Value>
    </Setting>
    <Setting Key="ima9ines.Nop.BaoKim.ReportBugsUri">
        <Value>https://github.com/ima9ines/nopCommerce/issues</Value>
    </Setting>
</Settings>
