<?xml version="1.0" encoding="utf-8" ?>
<Settings>
    <Setting Key="ima9ines.Nop.FeaturedProducts.PluginSeName">
        <Value>featured-products/</Value>
    </Setting>
    <Setting Key="ima9ines.Nop.FeaturedProducts.RateUri">
        <Value>http://www.nopcommerce.com/p/1705/featured-products-free-ima9inescom.aspx</Value>
    </Setting>
    <Setting Key="ima9ines.Nop.FeaturedProducts.SuggestFeaturesUri">
        <Value>http://ima9ines.com/featured-products</Value>
    </Setting>
    <Setting Key="ima9ines.Nop.FeaturedProducts.HelpUri">
        <Value>http://ima9ines.com/how-to-use-featured-products-plugin</Value>
    </Setting>
    <Setting Key="ima9ines.Nop.FeaturedProducts.ReportBugsUri">
        <Value>http://ima9ines.com/featured-products</Value>
    </Setting>
</Settings>
